.gitignore
LICENSE
errorcodes.txt
setup.py
fxcmrest/__init__.py
fxcmrest/config.py
fxcmrest/demo.json
fxcmrest/fxcmrest.py
fxcmrest/real.json
fxcmrest/socketio.py
fxcmrest/socketio_compat.py
fxcmrest.egg-info/PKG-INFO
fxcmrest.egg-info/SOURCES.txt
fxcmrest.egg-info/dependency_links.txt
fxcmrest.egg-info/requires.txt
fxcmrest.egg-info/top_level.txt
samples/Login.py
samples/PrintTable.py