Metadata-Version: 1.2
Name: fxcmrest
Version: 0.0.2a6
Summary: FXCM Rest API library for Python
Home-page: https://fxcm-pguz.github.io/fxcmrest-py/
Author: Pawel Guz
Author-email: pguz@fxcm.com
License: BSD
Download-URL: https://github.com/fxcm-pguz/fxcmrest-py
Keywords: FXCM REST API Wrapper Finance Algo Trading
Platform: UNKNOWN
Requires-Python: >=3.4
